LPCertLog/AndroidExportCSV.py
LPCertLog/LPCertReport.py
LPCertLog/LPCertReportUI.py
LPCertLog/TSListWidget.py
LPCertLog/WiFiExportCSV.py
LPCertLog/__init__.py
LPCertLog/iOSExportCSV.py
LPCertTool-0.0.6.dist-info/METADATA
LPCertTool-0.0.6.dist-info/WHEEL
LPCertTool-0.0.6.dist-info/entry_points.txt
LPCertTool-0.0.6.dist-info/top_level.txt
LPCertTool-0.0.6.dist-info/RECORD
