Metadata-Version: 2.1
Name: LPCertTool
Version: 0.0.6
Summary: Linkplay MSP Certificate Tool
Home-page: https://github.com/liuning0930
Author: Ning.Liu
Author-email: ning.liu@linkplay.com
License: UNKNOWN
Platform: UNKNOWN
Classifier: Programming Language :: Python :: 3
Classifier: License :: OSI Approved :: MIT License
Classifier: Operating System :: OS Independent
Requires-Python: >=3.0
Requires-Dist: PyQt5
Requires-Dist: XlsxWriter
Requires-Dist: xlrd
